{
  "id": "1",
  "totalNumberOfFetchedInstructions": "830576",
  "IPC": "0.436",
  "evenBecameEmptyAtCycle": "19034080",
  "threadFetchedInstructions": {
    "th0": "150069",
    "th1": "150069",
    "th2": "150069",
    "th3": "150069",
    "th4": "150069",
    "th5": "150069"
  },
  "l2Cache": {
    "rd000":{
      "miss": "0000032786",
      "access": "0000032795",
      "ratio": "099.97"
    },
    "wr000":{
      "miss": "0000032786",
      "access": "0000032795",
      "ratio": "099.97"
    },
    "rd001":{
      "miss": "0000032786",
      "access": "0000032795",
      "ratio": "099.97"
    },
    "wr001":{
      "miss": "0000032786",
      "access": "0000032795",
      "ratio": "099.97"
    }
  },
  "l1Cache": {
    "ird000": {
      "miss": "0000032786",
      "access": "0000032795",
      "ratio": "099.97"
    },
    "ird001": {
      "miss": "0000032786",
      "access": "0000032795",
      "ratio": "099.97"
    },
    "ird002": {
      "miss": "0000032786",
      "access": "0000032795",
      "ratio": "099.97"
    },
    "ird003": {
      "miss": "0000032786",
      "access": "0000032795",
      "ratio": "099.97"
    },
    "ird004": {
      "miss": "0000032786",
      "access": "0000032795",
      "ratio": "099.97"
    },
    "ird005": {
      "miss": "0000032786",
      "access": "0000032795",
      "ratio": "099.97"
    },

    "drd000": {
      "miss": "0000032786",
      "access": "0000032795",
      "ratio": "099.97"
    },
    "dwr000": {
      "miss": "0000032786",
      "access": "0000032795",
      "ratio": "099.97"
    },
    "drd001": {
      "miss": "0000032786",
      "access": "0000032795",
      "ratio": "099.97"
    },
    "dwr001": {
      "miss": "0000032786",
      "access": "0000032795",
      "ratio": "099.97"
    },
    "drd002": {
      "miss": "0000032786",
      "access": "0000032795",
      "ratio": "099.97"
    },
    "dwr002": {
      "miss": "0000032786",
      "access": "0000032795",
      "ratio": "099.97"
    },
    "drd003": {
      "miss": "0000032786",
      "access": "0000032795",
      "ratio": "099.97"
    },
    "dwr003": {
      "miss": "0000032786",
      "access": "0000032795",
      "ratio": "099.97"
    },
    "drd004": {
      "miss": "0000032786",
      "access": "0000032795",
      "ratio": "099.97"
    },
    "dwr004": {
      "miss": "0000032786",
      "access": "0000032795",
      "ratio": "099.97"
    },
    "drd005": {
      "miss": "0000032786",
      "access": "0000032795",
      "ratio": "099.97"
    },
    "dwr005": {
      "miss": "0000032786",
      "access": "0000032795",
      "ratio": "099.97"
    }
  }
}

