{
  "IPC": "0.436",
  "evenBecameEmptyAtCycle": "19034080",
  "totalNumberOfFetchedInstructions": "830576",
  "threadFetchedInstructions": {
    "th5": "150069",
    "th4": "150069",
    "th3": "150069",
    "th2": "190176",
    "th1": "75061",
    "th0": "115131"
  },
  "l1Cache": {
    "dwr005": {
      "access": "0000016393",
      "ratio": "099.97",
      "miss": "0000016388"
    },
    "dwr004": {
      "access": "0000016391",
      "ratio": "099.97",
      "miss": "0000016386"
    },
    "dwr003": {
      "access": "0000016391",
      "ratio": "099.97",
      "miss": "0000016386"
    },
    "dwr002": {
      "access": "0000024820",
      "ratio": "076.56",
      "miss": "0000019003"
    },
    "dwr001": {
      "access": "0000008199",
      "ratio": "099.94",
      "miss": "0000008194"
    },
    "dwr000": {
      "access": "0000016832",
      "ratio": "065.55",
      "miss": "0000011033"
    },
    "ird003": {
      "access": "0000002634",
      "ratio": "001.44",
      "miss": "0000000038"
    },
    "ird002": {
      "access": "0000006648",
      "ratio": "012.41",
      "miss": "0000000825"
    },
    "ird001": {
      "access": "0000001350",
      "ratio": "004.15",
      "miss": "0000000056"
    },
    "ird000": {
      "access": "0000005380",
      "ratio": "016.47",
      "miss": "0000000886"
    },
    "ird005": {
      "access": "0000002647",
      "ratio": "000.68",
      "miss": "0000000018"
    },
    "ird004": {
      "access": "0000002644",
      "ratio": "000.61",
      "miss": "0000000016"
    },
    "drd004": {
      "access": "0000032805",
      "ratio": "099.96",
      "miss": "0000032793"
    },
    "drd005": {
      "access": "0000032815",
      "ratio": "099.97",
      "miss": "0000032804"
    },
    "drd000": {
      "access": "0000026194",
      "ratio": "063.95",
      "miss": "0000016750"
    },
    "drd001": {
      "access": "0000016437",
      "ratio": "099.95",
      "miss": "0000016428"
    },
    "drd002": {
      "access": "0000042574",
      "ratio": "077.81",
      "miss": "0000033127"
    },
    "drd003": {
      "access": "0000032795",
      "ratio": "099.97",
      "miss": "0000032786"
    }
  },
  "l2Cache": {
    "wr000": {
      "access": "0000054693",
      "ratio": "099.16",
      "miss": "0000054231"
    },
    "wr001": {
      "access": "0000032774",
      "ratio": "100.00",
      "miss": "0000032773"
    },
    "rd001": {
      "access": "0000065631",
      "ratio": "099.98",
      "miss": "0000065621"
    },
    "rd000": {
      "access": "0000100896",
      "ratio": "099.82",
      "miss": "0000100710"
    }
  },
  "id": "1"
}